ufc_fighter_jung_chansung-0.2.1.dist-info/METADATA
ufc_fighter_jung_chansung-0.2.1.dist-info/WHEEL
ufc_fighter_jung_chansung/__init__.py
ufc_fighter_jung_chansung/lastdance.py
ufc_fighter_jung_chansung-0.2.1.dist-info/RECORD
