Metadata-Version: 2.1
Name: ufc-fighter-jung-chansung
Version: 0.2.1
Summary: In honor of the retirement of ufc fighter Jung Chan-sung...
Author-Email: dmario24 <data.mario24@gmail.com>
License: MIT
Requires-Python: >=3.7
